havoc_clustering_v2/__init__.py
havoc_clustering_v2/correlation_of_dlfv_groups.py
havoc_clustering_v2/feature_extractor.py
havoc_clustering_v2/havoc.py
havoc_clustering_v2/general_utility/image_creator.py
havoc_clustering_v2/general_utility/print_time.py
havoc_clustering_v2/general_utility/slide.py
havoc_clustering_v2/general_utility/tile_image_utils.py
havoc_clustering_v2/general_utility/unique_colors.py
havoc_clustering_v2/general_utility/ai/tileextractor.py
havoc_clustering_v2-0.0.11.dist-info/METADATA
havoc_clustering_v2-0.0.11.dist-info/WHEEL
havoc_clustering_v2-0.0.11.dist-info/licenses/LICENSE
havoc_clustering_v2-0.0.11.dist-info/RECORD
