Metadata-Version: 2.4
Name: havoc-clustering-v2
Version: 0.0.11
Summary: Histomic Atlases of Variation Of Cancers (HAVOC) is a versatile tool that helps map histomic heterogeneity across H&E-stained digital slide images to help guide regional deployment of molecular resources to the most relevant/biodiverse tumor niches
Project-URL: Homepage, https://bitbucket.org/diamandislabii/havoc
Author-email: Kevin Faust <kevin.faust@alumni.utoronto.ca>
License-File: LICENSE
Classifier: License :: OSI Approved :: GNU General Public License v3 (GPLv3)
Classifier: Operating System :: OS Independent
Classifier: Programming Language :: Python :: 3
Requires-Python: >=3.9
Requires-Dist: huggingface-hub
Requires-Dist: matplotlib
Requires-Dist: opencv-python
Requires-Dist: openslide-bin
Requires-Dist: openslide-python
Requires-Dist: pandas
Requires-Dist: scikit-learn
Requires-Dist: seaborn
Requires-Dist: umap-learn
